LICENSE
benchling_sdk/__init__.py
benchling_sdk/apps/__init__.py
benchling_sdk/apps/cli.py
benchling_sdk/apps/codegen/__init__.py
benchling_sdk/apps/codegen/generate_dependencies_module.py
benchling_sdk/apps/codegen/generate_models.py
benchling_sdk/apps/codegen/helpers.py
benchling_sdk/apps/codegen/templates/dependencies.py.jinja2
benchling_sdk/apps/codegen/templates/dropdown_model.py.jinja2
benchling_sdk/apps/codegen/templates/schema_instance_model.py.jinja2
benchling_sdk/apps/config/__init__.py
benchling_sdk/apps/config/dependencies.py
benchling_sdk/apps/config/mock_dependencies.py
benchling_sdk/apps/config/scalars.py
benchling_sdk/apps/helpers/__init__.py
benchling_sdk/apps/helpers/code_format_helpers.py
benchling_sdk/apps/helpers/config_helpers.py
benchling_sdk/apps/helpers/manifest_helpers.py
benchling_sdk/auth/__init__.py
benchling_sdk/auth/api_key_auth.py
benchling_sdk/auth/client_credentials_oauth2.py
benchling_sdk/benchling.py
benchling_sdk/cli.py
benchling_sdk/errors.py
benchling_sdk/helpers/__init__.py
benchling_sdk/helpers/client_helpers.py
benchling_sdk/helpers/decorators.py
benchling_sdk/helpers/file_helpers.py
benchling_sdk/helpers/logging_helpers.py
benchling_sdk/helpers/pagination_helpers.py
benchling_sdk/helpers/response_helpers.py
benchling_sdk/helpers/retry_helpers.py
benchling_sdk/helpers/serialization_helpers.py
benchling_sdk/helpers/transaction_manager.py
benchling_sdk/models/__init__.py
benchling_sdk/py.typed
benchling_sdk/services/__init__.py
benchling_sdk/services/aa_sequence_service.py
benchling_sdk/services/api_service.py
benchling_sdk/services/app_service.py
benchling_sdk/services/assay_result_service.py
benchling_sdk/services/assay_run_service.py
benchling_sdk/services/base_service.py
benchling_sdk/services/blob_service.py
benchling_sdk/services/box_service.py
benchling_sdk/services/container_service.py
benchling_sdk/services/custom_entity_service.py
benchling_sdk/services/dna_alignments_service.py
ce_bnch_sdk-2.2.0b0.dist-info/entry_points.txt
ce_bnch_sdk-2.2.0b0.dist-info/LICENSE
ce_bnch_sdk-2.2.0b0.dist-info/WHEEL
ce_bnch_sdk-2.2.0b0.dist-info/METADATA
ce_bnch_sdk-2.2.0b0.dist-info/RECORD
