Metadata-Version: 2.1
Name: ce-bnch-sdk
Version: 2.2.0b0
Summary: SDK for interacting with the Benchling Platform.
License: Apache-2.0
Author: Benchling Customer Engineering
Author-email: ce-team@benchling.com
Requires-Python: >=3.7,<4.0
Classifier: License :: OSI Approved :: Apache Software License
Classifier: Programming Language :: Python :: 3
Classifier: Programming Language :: Python :: 3.10
Classifier: Programming Language :: Python :: 3.7
Classifier: Programming Language :: Python :: 3.8
Classifier: Programming Language :: Python :: 3.9
Provides-Extra: app-scaffold
Requires-Dist: Jinja2 (>=3.1.0,<4.0.0); extra == "app-scaffold"
Requires-Dist: PyYAML (>=5.4.1,<6.0.0)
Requires-Dist: attrs (>=20.1.0,<=22.0)
Requires-Dist: autoflake (>=1.4,<2.0); extra == "app-scaffold"
Requires-Dist: backoff (>=1.10.0,<2.0.0)
Requires-Dist: benchling-api-client (==1.1.0a18)
Requires-Dist: black (>=22.3.0,<23.0.0); extra == "app-scaffold"
Requires-Dist: httpx (>=0.15.0,<=0.22.0)
Requires-Dist: python-dateutil (>=2.8.0,<3.0.0)
Requires-Dist: typer (>=0.4.0,<0.5.0); extra == "app-scaffold"
Requires-Dist: typing-extensions (>=3.7.4,<5.0)
